{
  "repository": "brunosbardelatti/bsqa-card-writer",
  "pr_number": 11,
  "title": "feat: add GitHub Actions workflow for automated code review",
  "head_branch": "feature/pipe_code_review",
  "base_branch": "release/v1.1.0",
  "status": "APROVADO",
  "reviewed_at": "2025-07-28T19:04:01Z",
  "analysis": "<details><summary>🔶 Sugestão: Padronização e segurança na configuração de secrets</summary>\n\n**Arquivo:** `.github/workflows/code-review.yml`  \n**Melhoria sugerida:**  \nOs secrets estão sendo referenciados com múltiplas chaves (`${{{{ secrets.SECRET_NAME }}}}`), o que pode ser um erro de sintaxe no GitHub Actions. O padrão correto é `${{ secrets.SECRET_NAME }}`. Além disso, é importante garantir que os secrets estejam corretamente configurados no repositório para evitar falhas na execução do workflow.\n\n**Trecho relacionado:**  \n```yaml\n      STACKSPOT_CLIENT_ID: ${{{{ secrets.STACKSPOT_CLIENT_ID }}}}\n      STACKSPOT_CLIENT_SECRET: ${{{{ secrets.STACKSPOT_CLIENT_SECRET }}}}\n      STACKSPOT_AGENT_ID: ${{{{ secrets.STACKSPOT_AGENT_ID }}}}\n      BSQA_GITHUB_TOKEN: ${{{{ secrets.BSQA_GITHUB_TOKEN }}}}\n```\n\n**Impacto positivo:**  \nCorrigir a sintaxe dos secrets evita falhas na execução do workflow e garante que as credenciais sejam passadas corretamente, aumentando a segurança e a confiabilidade do processo de automação.\n\n</details>\n\n<details><summary>🔶 Sugestão: Inclusão de `pull_request_target` para PRs de forks</summary>\n\n**Arquivo:** `.github/workflows/code-review.yml`  \n**Melhoria sugerida:**  \nSe o objetivo é analisar PRs vindos de forks, considere adicionar o evento `pull_request_target` para garantir que o workflow seja executado corretamente nesses casos. No entanto, avalie os riscos de segurança ao lidar com secrets em PRs de forks.\n\n**Trecho relacionado:**  \n```yaml\non:\n  pull_request:\n    types: [opened, synchronize, reopened]\n```\n\n**Impacto positivo:**  \nPermite que o workflow seja executado em PRs de forks, ampliando a cobertura da análise automatizada. Porém, é importante revisar as permissões de secrets para evitar exposição indevida.\n\n</details>\n\n<details><summary>🔶 Sugestão: Padronização do nome do arquivo e diretório</summary>\n\n**Arquivo:** `.github/workflows/codeReview/comment_template_code-review.md`  \n**Melhoria sugerida:**  \nO diretório `codeReview` utiliza camelCase, enquanto o padrão do GitHub Actions é usar nomes em minúsculo e separados por hífen (`-`). Recomenda-se renomear para `code-review` para manter a consistência e facilitar a manutenção.\n\n**Trecho relacionado:**  \n```\n.github/workflows/codeReview/comment_template_code-review.md\n```\n\n**Impacto positivo:**  \nFacilita a navegação, manutenção e evita possíveis problemas de case sensitivity em sistemas de arquivos diferentes.\n\n</details>\n\n<details><summary>🔶 Sugestão: Padronização de variáveis no template de comentário</summary>\n\n**Arquivo:** `.github/workflows/codeReview/comment_template_code-review.md`  \n**Melhoria sugerida:**  \nAs variáveis do template estão usando múltiplas chaves (`{{{{VAR}}}}`). Certifique-se de que o sistema que processa esse template está preparado para esse padrão, ou considere padronizar para o formato mais comum (`{{VAR}}`).\n\n**Trecho relacionado:**  \n```markdown\n**PR:** #{{{{PR_NUMBER}}}}  \n**Título:** {{{{PR_TITLE}}}}  \n**Branch:** `{{{{HEAD}}}}` → `{{{{BASE}}}}`  \n...\n{{{{REVIEW_CONTENT}}}}\n...\n_Gerado em {{{{DATE}}}} (Horário de Brasília)_\n```\n\n**Impacto positivo:**  \nEvita falhas na renderização do template e melhora a legibilidade e manutenção do código.\n\n</details>\n\n---\n\n### Resumo\n\nNenhum problema crítico foi identificado, apenas sugestões de melhorias para padronização, segurança e manutenção.\n\n**Status:**  \n`APROVADO`\n"
}
